slacraper/__init__.py
slacraper/_version.py
slacraper/cli.py
slacraper/core.py
slacraper-0.2.1.dist-info/licenses/LICENSE
slacraper-0.2.1.dist-info/METADATA
slacraper-0.2.1.dist-info/WHEEL
slacraper-0.2.1.dist-info/entry_points.txt
slacraper-0.2.1.dist-info/top_level.txt
slacraper-0.2.1.dist-info/RECORD
