Metadata-Version: 2.4
Name: slacraper
Version: 0.2.1
Summary: Slack message scraper tool
Author: youyo
License: MIT License
Classifier: Programming Language :: Python :: 3.12
Classifier: Development Status :: 4 - Beta
Classifier: Intended Audience :: Developers
Classifier: License :: OSI Approved :: MIT License
Classifier: Topic :: Communications :: Chat
Classifier: Topic :: Utilities
Requires-Python: >=3.12.0
License-File: LICENSE
Requires-Dist: slack-sdk>=3.0.0
Requires-Dist: click>=8.0.0
Requires-Dist: python-dateutil>=2.8.2
Provides-Extra: test
Requires-Dist: pytest>=7.0.0; extra == "test"
Requires-Dist: pytest-cov>=4.0.0; extra == "test"
Provides-Extra: dev
Requires-Dist: black>=23.0.0; extra == "dev"
Requires-Dist: isort>=5.0.0; extra == "dev"
Requires-Dist: mypy>=1.0.0; extra == "dev"
Dynamic: author
Dynamic: license-file
Dynamic: requires-python
